{
  "data": {
    "type": "law",
    "id": "BJNR210370989",
    "firstPublished": "1988-01-26",
    "sourceTimestamp": "20120625145700",
    "titleShort": null,
    "titleLong": "Abkommen zwischen der Regierung der Bundesrepublik Deutschland und der\nRegierung der Tschechoslowakischen Sozialistischen Republik \u00fcber den\nBinnenschiffsverkehr",
    "abbreviation": "BinSchAbk CSK",
    "slug": "binschabk_csk",
    "extraAbbreviations": [],
    "publicationInfo": [
      {
        "reference": "1989, 1037",
        "periodical": "BGBl II"
      }
    ],
    "statusInfo": [],
    "notes": {
      "body": null,
      "footnotes": null,
      "documentaryFootnotes": "<P>G v. 14.12.1989 II 1035 <BR />Inkraft gem. Bek. v. 13.6.1990 II 631 mWv 4.5.1990</P>"
    },
    "attachments": {},
    "contents": []
  }
}
