{
  "data": {
    "type": "law",
    "id": "BJNR239100998",
    "firstPublished": "1998-08-24",
    "sourceTimestamp": "20210930213128",
    "titleShort": null,
    "titleLong": "Verordnung \u00fcber die Zuweisung von Aufgaben und Befugnissen einer\nEntsch\u00e4digungseinrichtung an die Entsch\u00e4digungseinrichtung\ndeutscher Banken GmbH",
    "abbreviation": "EntschdtBankV",
    "slug": "entschdtbankv",
    "extraAbbreviations": [],
    "publicationInfo": [
      {
        "reference": "1998, 2391",
        "periodical": "BGBl I"
      }
    ],
    "statusInfo": [
      {
        "comment": "Zuletzt ge\u00e4ndert durch Art. 1 V v. 8.6.2021 I 1711",
        "category": "Stand"
      }
    ],
    "notes": {
      "body": null,
      "footnotes": null,
      "documentaryFootnotes": "<P>(+++ Textnachweis ab: 28. 8.1998 +++)</P>"
    },
    "attachments": {},
    "contents": [
      {
        "type": "article",
        "id": "BJNR239100998BJNE000100311",
        "name": "Eingangsformel",
        "title": null,
        "parent": null,
        "body": "<P>Auf Grund des \u00a7 7 Abs. 1 Satz 1 und 3 des Einlagensicherungs- und Anlegerentsch\u00e4digungsgesetzes vom 16. Juli 1998 (BGBl. I S. 1842) verordnet das Bundesministerium der Finanzen:</P>",
        "footnotes": null,
        "documentaryFootnotes": null
      },
      {
        "type": "article",
        "id": "BJNR239100998BJNE000202123",
        "name": "\u00a7 1",
        "title": null,
        "parent": null,
        "body": "<P>Der Entsch\u00e4digungseinrichtung deutscher Banken GmbH werden die Aufgaben und Befugnisse der gesetzlichen Entsch\u00e4digungseinrichtung f\u00fcr alle ihr nach \u00a7 24 Absatz 2 des Einlagensicherungsgesetzes zugeordneten CRR-Kreditinstitute zugewiesen.</P>",
        "footnotes": null,
        "documentaryFootnotes": null
      },
      {
        "type": "article",
        "id": "BJNR239100998BJNE000300311",
        "name": "\u00a7 2",
        "title": null,
        "parent": null,
        "body": "<P>Die Entsch\u00e4digungseinrichtung deutscher Banken GmbH hat dem Bundesministerium der Finanzen \u00c4nderungen des Gesellschaftsvertrags zur Genehmigung vorzulegen.</P>",
        "footnotes": null,
        "documentaryFootnotes": null
      },
      {
        "type": "article",
        "id": "BJNR239100998BJNE000500123",
        "name": "\u00a7 2a",
        "title": null,
        "parent": null,
        "body": "<P>Die Entsch\u00e4digungseinrichtung deutscher Banken GmbH folgt der Entsch\u00e4digungseinrichtung des Bundesverbandes \u00d6ffentlicher Banken Deutschlands GmbH im Sinne des \u00a7 25a Absatz 2 Satz 1 des Einlagensicherungsgesetzes nach.</P>",
        "footnotes": null,
        "documentaryFootnotes": null
      },
      {
        "type": "article",
        "id": "BJNR239100998BJNE000400311",
        "name": "\u00a7 3",
        "title": null,
        "parent": null,
        "body": "<P>Diese Verordnung tritt am Tage nach der Verk\u00fcndung in Kraft.</P>",
        "footnotes": null,
        "documentaryFootnotes": null
      }
    ]
  }
}
