{
  "data": {
    "type": "law",
    "id": "BJNR133620006",
    "firstPublished": "2006-03-09",
    "sourceTimestamp": "20120625152608",
    "titleShort": null,
    "titleLong": "Verwaltungsvereinbarung zwischen dem Bundesministerium f\u00fcr Gesundheit der Bundesrepublik Deutschland und dem Minister f\u00fcr Gesundheit und Solidarit\u00e4t der Franz\u00f6sischen Republik \u00fcber die Durchf\u00fchrungsmodalit\u00e4ten des Rahmenabkommens vom 22. Juli 2005 \u00fcber die grenz\u00fcberschreitende Zusammenarbeit im Gesundheitsbereich",
    "abbreviation": "GesundZAAbkFRAVVbg",
    "slug": "gesundzaabkfravvbg",
    "extraAbbreviations": [],
    "publicationInfo": [
      {
        "reference": "2006, 1336",
        "periodical": "BGBl II"
      }
    ],
    "statusInfo": [],
    "notes": {
      "body": null,
      "footnotes": null,
      "documentaryFootnotes": "<P>G v. 17.12.2006 II 1330 <BR />In Kraft gem. Bek. v. 3.8.2007 II 1461 mWv 1.5.2007</P>"
    },
    "attachments": {},
    "contents": []
  }
}
