{
  "data": {
    "type": "law",
    "id": "BJNR518210995",
    "firstPublished": "1995-09-06",
    "sourceTimestamp": "20130325220025",
    "titleShort": null,
    "titleLong": "Hundertf\u00fcnfundf\u00fcnfzigste Durchf\u00fchrungsverordnung zur Luftverkehrs-Ordnung (Festlegung von Flugverfahren f\u00fcr An- und Abfl\u00fcge nach Instrumentenflugregeln zum und vom Verkehrslandeplatz Leipzig-Altenburg Airport)",
    "abbreviation": "LuftVODV 155",
    "slug": "luftvodv_155",
    "extraAbbreviations": [],
    "publicationInfo": [
      {
        "reference": "1995, Nr 182, 10722",
        "periodical": "BAnz"
      },
      {
        "reference": "1995, 10722",
        "periodical": "BAnz"
      }
    ],
    "statusInfo": [],
    "notes": {
      "body": null,
      "footnotes": null,
      "documentaryFootnotes": "<P>Wegen nicht darstellbarer Zeichen nur mit der \u00dcberschrift aufgenommen <BR /> \u00dcberschrift: IdF d. Art. 1 Nr. 1 V v. 11.2.2009 BAnz 2009, Nr 31, 679 mWv 12.3.2009</P>"
    },
    "attachments": {},
    "contents": []
  }
}
