{
  "data": {
    "type": "law",
    "id": "BJNR029110975",
    "firstPublished": "1975-11-21",
    "sourceTimestamp": "20160617215512",
    "titleShort": null,
    "titleLong": "Bekanntmachung zu \u00a7 4 des Warenzeichengesetzes",
    "abbreviation": "WZG\u00a74NLDBek 1975",
    "slug": "wzg_4nldbek_1975",
    "extraAbbreviations": [],
    "publicationInfo": [
      {
        "reference": "1975, 2911",
        "periodical": "BGBl I"
      }
    ],
    "statusInfo": [],
    "notes": {
      "body": null,
      "footnotes": null,
      "documentaryFootnotes": "<P>(+++ Textnachweis ab: 28.11.1975 +++)</P>"
    },
    "attachments": {
      "bgbl1_1975_j2912_0010.jpg": "https://fellows-2020-rechtsinfo-assets.s3.eu-central-1.amazonaws.com/public/gesetze_im_internet/wzg_4nldbek_1975/bgbl1_1975_j2912_0010.jpg"
    },
    "contents": [
      {
        "type": "article",
        "id": "BJNR029110975BJNE000100303",
        "name": "(XXXX)",
        "title": null,
        "parent": null,
        "body": "<P>(1) Auf Grund des \u00a7 4 Abs. 2 Nr. 3 des Warenzeichengesetzes in der Fassung der Bekanntmachung vom 2. Januar 1968 (Bundesgesetzbl. I S. 1, 29), zuletzt ge\u00e4ndert durch das Gesetz vom 9. Dezember 1974 (Bundesgesetzbl. I S. 3416), werden in der Anlage 1 amtliche Pr\u00fcf- und Gew\u00e4hrzeichen f\u00fcr Butter und Milchpulver bekanntgemacht, die im K\u00f6nigreich der Niederlande eingef\u00fchrt sind.</P><P>(2) Diese Bekanntmachung ergeht im Anschlu\u00df an die Bekanntmachung vom 21. Juli 1975 (Bundesgesetzblatt I S. 1946).</P>",
        "footnotes": null,
        "documentaryFootnotes": null
      },
      {
        "type": "article",
        "id": "BJNR029110975BJNE000900303",
        "name": "Schlussformel",
        "title": null,
        "parent": null,
        "body": "<P>Der Bundesminister der Justiz</P>",
        "footnotes": null,
        "documentaryFootnotes": null
      },
      {
        "type": "article",
        "id": "BJNR029110975BJNE000200303",
        "name": "Anlage 1",
        "title": null,
        "parent": null,
        "body": "<P><noindex><kommentar typ=\"Fundstelle\">(Fundstelle: BGBl. I 1975, 2912)</kommentar></noindex><IMG Align=\"center\" Pos=\"block\" SRC=\"bgbl1_1975_j2912_0010.jpg\" /></P>",
        "footnotes": null,
        "documentaryFootnotes": null
      },
      {
        "type": "article",
        "id": "BJNR029110975BJNE000300303",
        "name": "Anlage 2",
        "title": null,
        "parent": null,
        "body": null,
        "footnotes": null,
        "documentaryFootnotes": null
      }
    ]
  }
}
