{
  "data": {
    "type": "law",
    "id": "BJNR040000097",
    "firstPublished": "1997-09-12",
    "sourceTimestamp": "20120625155435",
    "titleShort": null,
    "titleLong": "\u00dcbereinkommen \u00fcber zus\u00e4tzliche Entsch\u00e4digungsleistungen f\u00fcr nuklearen \nSchaden",
    "abbreviation": "ZusEntschLnuklSch\u00dcbk",
    "slug": "zusentschlnuklschuebk",
    "extraAbbreviations": [],
    "publicationInfo": [],
    "statusInfo": [],
    "notes": {
      "body": null,
      "footnotes": null,
      "documentaryFootnotes": null
    },
    "attachments": {},
    "contents": []
  }
}
