{
  "data": {
    "type": "law",
    "id": "BJNR133420010",
    "firstPublished": "2010-03-30",
    "sourceTimestamp": "20120625154716",
    "titleShort": null,
    "titleLong": "Abkommen zwischen der Bundesrepublik Deutschland und dem Vereinigten K\u00f6nigreich Gro\u00dfbritannien und Nordirland zur Vermeidung der Doppelbesteuerung und zur Verhinderung der Steuerverk\u00fcrzung auf dem Gebiet der Steuern vom Einkommen und vom Verm\u00f6gen",
    "abbreviation": "DBAAbk GBR",
    "slug": "dbaabk_gbr",
    "extraAbbreviations": [],
    "publicationInfo": [
      {
        "reference": "2010, 1334",
        "periodical": "BGBl II"
      }
    ],
    "statusInfo": [],
    "notes": {
      "body": null,
      "footnotes": null,
      "documentaryFootnotes": "<P>G v. 18.11.2010 II 1333 <BR />In Kraft gem. Bek. v. 12.4.2011 II 536 mWv 30.12.2010</P>"
    },
    "attachments": {},
    "contents": []
  }
}
