{
  "data": {
    "type": "law",
    "id": "BJNR212300993",
    "firstPublished": "1993-12-17",
    "sourceTimestamp": "20120625154825",
    "titleShort": "Planungsvereinfachungsgesetz",
    "titleLong": "Gesetz zur Vereinfachung der Planungsverfahren f\u00fcr Verkehrswege",
    "abbreviation": "PlVereinfG",
    "slug": "plvereinfg",
    "extraAbbreviations": [],
    "publicationInfo": [
      {
        "reference": "1993, 2123",
        "periodical": "BGBl I"
      }
    ],
    "statusInfo": [],
    "notes": {
      "body": null,
      "footnotes": null,
      "documentaryFootnotes": "<P>(+++ Textnachweis ab: 24.12.1993 +++)</P>"
    },
    "attachments": {},
    "contents": [
      {
        "type": "article",
        "id": "BJNR212300993BJNE000100307",
        "name": "Eingangsformel",
        "title": null,
        "parent": null,
        "body": "<P>Der Bundestag hat mit Zustimmung des Bundesrates das folgende Gesetz beschlossen:</P>",
        "footnotes": null,
        "documentaryFootnotes": null
      },
      {
        "type": "article",
        "id": "BJNR212300993BJNE000200307",
        "name": "(XXXX) Art 1 bis 9",
        "title": null,
        "parent": null,
        "body": null,
        "footnotes": null,
        "documentaryFootnotes": null
      },
      {
        "type": "article",
        "id": "BJNR212300993BJNE000300307",
        "name": "Art 10",
        "title": "\u00dcbergangsregelungen",
        "parent": null,
        "body": "<P>Vor Inkrafttreten dieses Gesetzes begonnene Planungsverfahren werden nach den Vorschriften dieses Gesetzes weitergef\u00fchrt. \u00a7 36d Abs. 6 des Bundesbahngesetzes, \u00a7 17 Abs. 6c des Bundesfernstra\u00dfengesetzes, \u00a7 19 Abs. 4 des Bundeswasserstra\u00dfengesetzes, \u00a7 10 Abs. 8 des Luftverkehrsgesetzes und \u00a7 29 Abs. 8 des Personenbef\u00f6rderungsgesetzes in der Fassung dieses Gesetzes sind auch in verwaltungsgerichtlichen Verfahren anzuwenden, bei denen die angefochtene Entscheidung vor dem Inkrafttreten dieses Gesetzes erlassen worden ist.</P>",
        "footnotes": null,
        "documentaryFootnotes": null
      },
      {
        "type": "article",
        "id": "BJNR212300993BJNE000400307",
        "name": "Art 11",
        "title": "Neubekanntmachung",
        "parent": null,
        "body": null,
        "footnotes": null,
        "documentaryFootnotes": null
      },
      {
        "type": "article",
        "id": "BJNR212300993BJNE000500307",
        "name": "Art 12",
        "title": "Inkrafttreten",
        "parent": null,
        "body": "<P>Dieses Gesetz tritt am Tage nach der Verk\u00fcndung in Kraft.</P>",
        "footnotes": null,
        "documentaryFootnotes": null
      }
    ]
  }
}
